datawhisperer/__init__.py
datawhisperer/core.py
datawhisperer/core_types.py
datawhisperer/code_executor/__init__.py
datawhisperer/code_executor/executor.py
datawhisperer/code_executor/fixer.py
datawhisperer/llm_client/__init__.py
datawhisperer/llm_client/gemini_client.py
datawhisperer/llm_client/openai_client.py
datawhisperer/prompt_engine/__init__.py
datawhisperer/prompt_engine/prompt_cache.py
datawhisperer/prompt_engine/prompt_factory.py
datawhisperer-0.1.4.dist-info/licenses/LICENSE
datawhisperer-0.1.4.dist-info/METADATA
datawhisperer-0.1.4.dist-info/WHEEL
datawhisperer-0.1.4.dist-info/top_level.txt
datawhisperer-0.1.4.dist-info/RECORD
