Metadata-Version: 2.4
Name: datawhisperer
Version: 0.1.4
Summary: Natural language interface for DataFrames using LLMs
Author-email: JosueARz <josueayalaruiz@gmail.com>
License-Expression: Apache-2.0
Project-URL: Homepage, https://github.com/JosueARz/datawhisperer
Project-URL: Bug Tracker, https://github.com/JosueARz/datawhisperer/issues
Keywords: LLM,DataFrame,pandas,chatbot,OpenAI,Gemini
Classifier: Development Status :: 3 - Alpha
Classifier: Intended Audience :: Developers
Classifier: Topic :: Scientific/Engineering :: Artificial Intelligence
Classifier: Programming Language :: Python :: 3.8
Classifier: Programming Language :: Python :: 3.9
Classifier: Programming Language :: Python :: 3.10
Classifier: Programming Language :: Python :: 3.11
Requires-Python: >=3.8
License-File: LICENSE
Requires-Dist: openai>=0.28.0
Requires-Dist: pandas>=2.2.0
Requires-Dist: plotly>=5.0.0
Requires-Dist: google-generativeai>=0.8.0
Provides-Extra: dev
Requires-Dist: pytest; extra == "dev"
Requires-Dist: pytest-cov; extra == "dev"
Requires-Dist: black; extra == "dev"
Requires-Dist: isort; extra == "dev"
Dynamic: license-file
